{
  "auth": "zef:lizmat",
  "authors": [
    "Elizabeth Mattijsen"
  ],
  "build-depends": [
  ],
  "depends": [
    "Hash::Agnostic:ver<0.0.17>:auth<zef:lizmat>"
  ],
  "description": "role for ordered Hashes",
  "license": "Artistic-2.0",
  "name": "Hash::Ordered",
  "perl": "6.c",
  "provides": {
    "Hash::Ordered": "lib/Hash/Ordered.rakumod"
  },
  "resources": [
  ],
  "source-url": "https://github.com/lizmat/Hash-Ordered.git",
  "tags": [
    "UTILS"
  ],
  "test-depends": [
  ],
  "version": "0.0.8"
}
